portalsmp/__init__.py
portalsmp/collections_ids.py
portalsmp/portalsapi.py
portalsmp-1.2.dist-info/METADATA
portalsmp-1.2.dist-info/WHEEL
portalsmp-1.2.dist-info/top_level.txt
portalsmp-1.2.dist-info/RECORD
