Metadata-Version: 2.4
Name: portalsmp
Version: 1.2
Summary: A Python Module for interacting with Portals Marketplace API
Home-page: https://github.com/bleach-hub/portalsmp
Author: bleach
Author-email: year0001@internet.ru
Classifier: Programming Language :: Python :: 3
Classifier: License :: OSI Approved :: MIT License
Requires-Python: >=3.8
Requires-Dist: kurigram>=2.2.6
Requires-Dist: curl_cffi>=0.10.0
Dynamic: author
Dynamic: author-email
Dynamic: classifier
Dynamic: description
Dynamic: description-content-type
Dynamic: home-page
Dynamic: requires-dist
Dynamic: requires-python
Dynamic: summary
